README.rst
setup.py
myLabTools/__init__.py
myLabTools/decorators.py
myLabTools/files.py
myLabTools/tools.py
myLabTools.egg-info/PKG-INFO
myLabTools.egg-info/SOURCES.txt
myLabTools.egg-info/dependency_links.txt
myLabTools.egg-info/requires.txt
myLabTools.egg-info/top_level.txt
myLabTools/brat_tool/__init__.py
myLabTools/brat_tool/brat2json.py
myLabTools/brat_tool/brat_util.py
myLabTools/cnki/__init__.py
myLabTools/cnki/article.py
myLabTools/cnki/xml2html.py
myLabTools/db/__init__.py
myLabTools/db/mongodb.py
myLabTools/db/multi_process.py
myLabTools/db/mysqldb.py
myLabTools/ner/__init__.py
myLabTools/ner/load_ner_jsonline_dataset.py
myLabTools/ner/ner_metric.py
myLabTools/nlp/__init__.py
myLabTools/nlp/coref.py
myLabTools/nlp/data_process.py
myLabTools/nlp/es_index.py
myLabTools/nlp/json2bieo.py
myLabTools/nlp/ner_format_trans.py
myLabTools/nlp/paragraph_split.py
myLabTools/nlp/text_encoder.py
myLabTools/nlp/tools.py
myLabTools/nlp/utils_ner.py
myLabTools/nlp/wordcollocation_based_mi.py
myLabTools/sciie/__init__.py
myLabTools/sciie/entity_rel_post_process.py
myLabTools/sciie/predictor.py
myLabTools/sciie/script.py
myLabTools/sciie/spert/__init__.py
myLabTools/sciie/spert/custom_tokenizer.py
myLabTools/sciie/spert/entities.py
myLabTools/sciie/spert/evaluator.py
myLabTools/sciie/spert/input_reader.py
myLabTools/sciie/spert/loss.py
myLabTools/sciie/spert/models.py
myLabTools/sciie/spert/opt.py
myLabTools/sciie/spert/prediction.py
myLabTools/sciie/spert/sampling.py
myLabTools/sciie/spert/spert_trainer.py
myLabTools/sciie/spert/trainer.py
myLabTools/sciie/spert/util.py
myLabTools/sciie/spert/util_2.py
myLabTools/spider/__init__.py
myLabTools/spider/logger_base.py
myLabTools/spider/proxy_base.py
myLabTools/spider/spider_base.py
myLabTools/t2s/__init__.py
myLabTools/t2s/conv_tra2sim.py
myLabTools/t2s/langconv.py
myLabTools/t2s/zh_wiki.py
myLabTools/text_classification/__init__.py
myLabTools/text_classification/bert_model.py
myLabTools/text_classification/bert_text_classify_pipeline.py
myLabTools/text_classification/lime_xai.py
myLabTools/text_classification/predict_on_raw_data.py
myLabTools/text_classification/train_text_clf_model.py
